videre/__init__.py
videre/colors.py
videre/dialog.py
videre/gradient.py
videre/tools.py
videre/core/__init__.py
videre/core/clipboard.py
videre/core/constants.py
videre/core/events.py
videre/core/mouse_ownership.py
videre/core/position_mapping.py
videre/core/pygame_utils.py
videre/core/utils.py
videre/core/fontfactory/__init__.py
videre/core/fontfactory/font_factory_utils.py
videre/core/fontfactory/pygame_font_factory.py
videre/core/fontfactory/pygame_text_rendering.py
videre/core/sides/__init__.py
videre/core/sides/abstract_sides.py
videre/core/sides/border.py
videre/core/sides/margin.py
videre/core/sides/padding.py
videre/fonts/__init__.py
videre/fonts/_gen_char_cov.py
videre/fonts/_gen_info.py
videre/fonts/char-support.json
videre/fonts/char-support_old.json
videre/fonts/compare.py
videre/fonts/font_utils.py
videre/fonts/indent.py
videre/fonts/unicode_utils.py
videre/fonts/noto/unhinted/TTF/NotoEmoji-Regular.ttf
videre/fonts/noto/unhinted/TTF/NotoFangsongKSSVertical-Regular.ttf
videre/fonts/noto/unhinted/TTF/NotoMusic-Regular.ttf
videre/fonts/noto/unhinted/TTF/NotoNastaliqUrdu-Regular.ttf
videre/fonts/noto/unhinted/TTF/NotoSans-Regular.ttf
videre/fonts/noto/unhinted/TTF/NotoSansAdlam-Regular.ttf
videre/fonts/noto/unhinted/TTF/NotoSansAnatolianHieroglyphs-Regular.ttf
videre/fonts/noto/unhinted/TTF/NotoSansArabic-Regular.ttf
videre/fonts/noto/unhinted/TTF/NotoSansArmenian-Regular.ttf
videre/fonts/noto/unhinted/TTF/NotoSansAvestan-Regular.ttf
videre/fonts/noto/unhinted/TTF/NotoSansBalinese-Regular.ttf
videre/fonts/noto/unhinted/TTF/NotoSansBamum-Regular.ttf
videre/fonts/noto/unhinted/TTF/NotoSansBassaVah-Regular.ttf
videre/fonts/noto/unhinted/TTF/NotoSansBatak-Regular.ttf
videre/fonts/noto/unhinted/TTF/NotoSansBengali-Regular.ttf
videre/fonts/noto/unhinted/TTF/NotoSansBhaiksuki-Regular.ttf
videre/fonts/noto/unhinted/TTF/NotoSansBrahmi-Regular.ttf
videre/fonts/noto/unhinted/TTF/NotoSansBuginese-Regular.ttf
videre/fonts/noto/unhinted/TTF/NotoSansBuhid-Regular.ttf
videre-0.1.0.dist-info/METADATA
videre-0.1.0.dist-info/WHEEL
videre-0.1.0.dist-info/RECORD
